keops/__init__.py
keops/clip.py
keops/erase.py
keops/main.py
keops/size.py
keops/src/__init__.py
keops/src/mvt_clipper.py
keops/src/mvt_eraser.py
keops/src/mvt_metrics_logger.py
keops/src/mvt_optimizer.py
keops/src/mvt_reader.py
keops/src/mvt_writer.py
keops/src/utils.py
keops_tiles-0.0.1.dist-info/LICENSE.md
keops_tiles-0.0.1.dist-info/METADATA
keops_tiles-0.0.1.dist-info/WHEEL
keops_tiles-0.0.1.dist-info/entry_points.txt
keops_tiles-0.0.1.dist-info/top_level.txt
keops_tiles-0.0.1.dist-info/RECORD
