Metadata-Version: 2.1
Name: keops-tiles
Version: 0.0.1
Summary: CLI tool for custom edition and management of Mapbox Vector Tiles in MBTiles format
Author-email: Fran Martín <fmartinrivas2@gmail.com>
License: MIT
Project-URL: Homepage, https://github.com/fmariv/keops-tiles
Project-URL: Bug Tracker, https://github.com/fmariv/keops-tiles/issues
Keywords: mbtiles,python,vector-tiles
Classifier: Programming Language :: Python :: 3
Classifier: License :: OSI Approved :: MIT License
Classifier: Operating System :: OS Independent
Requires-Python: >=3.7
License-File: LICENSE.md
Requires-Dist: Click
Requires-Dist: mapbox-vector-tile (==1.2.1)
Requires-Dist: protobuf (==3.19.4)
